MANIFEST.in
README.md
setup.cfg
setup.py
eva/__init__.py
eva/exception.py
eva/conf/__init__.py
eva/conf/global_settings.py
eva/conf/locale/__init__.py
eva/management/__init__.py
eva/management/common.py
eva/management/commands/__init__.py
eva/utils/__init__.py
eva/utils/convert.py
eva/utils/debug.py
eva/utils/dict.py
eva/utils/functional.py
eva/utils/random_.py
eva/utils/time_.py
pyeva.egg-info/PKG-INFO
pyeva.egg-info/SOURCES.txt
pyeva.egg-info/dependency_links.txt
pyeva.egg-info/requires.txt
pyeva.egg-info/top_level.txt