Metadata-Version: 2.1
Name: pyeva
Version: 3.0.0
Summary: A microservices framework base on tornado
Home-page: https://github.com/ooclab/eva
Author: ooclab
Author-email: info@ooclab.com
License: MIT
Keywords: microservices pyeva web framework ooclab
Platform: any
Classifier: Development Status :: 5 - Production/Stable
Classifier: Intended Audience :: Developers
Classifier: Topic :: Software Development :: Libraries :: Application Frameworks
Classifier: License :: OSI Approved :: MIT License
Classifier: Programming Language :: Python :: 3
Provides-Extra: test
Provides-Extra: dev
